plover_custom_folding/EngineGetterExtension.py
plover_custom_folding/PythonDictionary.py
plover_custom_folding/PythonFoldingDictionary.py
plover_custom_folding/__init__.py
plover_custom_folding/lib/Rule.py
plover_custom_folding/lib/builder.py
plover_custom_folding/lib/util.py
plover_custom_folding-0.0.1.dist-info/METADATA
plover_custom_folding-0.0.1.dist-info/WHEEL
plover_custom_folding-0.0.1.dist-info/entry_points.txt
plover_custom_folding-0.0.1.dist-info/top_level.txt
plover_custom_folding-0.0.1.dist-info/zip-safe
plover_custom_folding-0.0.1.dist-info/RECORD
